[
  {
    "id": "92e38a91-4184-420a-b6d0-8a76fe7b02ac",
    "flow": "UserCreation",
    "method": "POST",
    "endpoint": "/v3/users",
    "status": 400,
    "headers": {
      "Content-Type": "application/json"
    },
    "body": {
      "errorCode": 1001,
      "httpCode": 400,
      "message": "Email required.",
      "environment": "uat",
      "errorContext": "Shipyard.Users.Services",
      "transactionTime": "2025-07-04T14:25:14.521244Z",
      "transactionId": "a5a67a4d-01b1-44d8-8d17-ef8702cd3b61"
    },
    "active": true,
    "endpointUrl": "public-ubiservices.ubi.com",
    "delay": 0
  }
]